BinTut-0.3.3.dist-info/DESCRIPTION.rst
BinTut-0.3.3.dist-info/LICENSE.txt
BinTut-0.3.3.dist-info/METADATA
BinTut-0.3.3.dist-info/RECORD
BinTut-0.3.3.dist-info/WHEEL
BinTut-0.3.3.dist-info/entry_points.txt
BinTut-0.3.3.dist-info/metadata.json
BinTut-0.3.3.dist-info/top_level.txt
bintut/__init__.py
bintut/__main__.py
bintut/entry.py
bintut/main.py
bintut/version.txt
bintut/courses/__init__.py
bintut/courses/debuggers.py
bintut/courses/exploits.py
bintut/courses/init.py
bintut/courses/main.py
bintut/courses/repl.py
bintut/courses/utils.py
bintut/courses/targets/__init__.py
bintut/courses/targets/fread-nx_off-canary_off-x64
bintut/courses/targets/fread-nx_off-canary_off-x86
bintut/courses/targets/fread-nx_on-canary_off-x64
bintut/courses/targets/fread-nx_on-canary_off-x86
bintut/courses/targets/winx86.exe
